signlanguage/__init__.py
signlanguage/signlanguage.py
signlanguage/core/__init__.py
signlanguage/core/core_class.py
signlanguage/core/executionmodel_class.py
signlanguage/core/trainmodel_class.py
signlanguage/core/v3/__init__.py
signlanguage/core/v3/core_class.py
signlanguage/core/v3/executionmodel_class.py
signlanguage/core/v3/trainmodel_class.py
signlanguage/interfaces/__init__.py
signlanguage/interfaces/interfaces_model.py
signlanguage/interfaces/transfermodel_class.py
signlanguage/models/__init__.py
signlanguage/models/handmodel_class.py
signlanguage/models/movementmodel_class.py
signlanguage/models/signmodel_class.py
signlanguage/models/statemodel_class.py
signlanguage/models/v2/__init__.py
signlanguage/models/v2/handmodel_class.py
signlanguage/models/v3/__init__.py
signlanguage/models/v3/handmodel_class.py
signlanguage/models/v3/signmodel_class.py
signlanguage/utils/__init__.py
signlanguage/utils/transfer_class.py
signlanguage/utils/utils_class.py
signlanguage/v3/__init__.py
signlanguage/v3/signlanguage.py
signlanguage-0.2.0.dist-info/LICENSE.md
signlanguage-0.2.0.dist-info/METADATA
signlanguage-0.2.0.dist-info/WHEEL
signlanguage-0.2.0.dist-info/top_level.txt
signlanguage-0.2.0.dist-info/RECORD
