Metadata-Version: 2.1
Name: signlanguage
Version: 0.2.0
Summary: Paquete para administracion de la informacion de datos para reconocer señales realizadas con las manos - (model-3)
Home-page: https://github.com/JoWan1998/signlanguage
Author: Jose Orlando Wannan Escobar
Author-email: Jose Orlando Wannan Escobar <jwannan13@gmail.com>
Project-URL: Homepage, https://github.com/JoWan1998/signlanguage
Project-URL: Bug Tracker, https://github.com/JoWan1998/signlanguage/issues
Classifier: Development Status :: 4 - Beta
Classifier: License :: OSI Approved :: GNU General Public License v3 or later (GPLv3+)
Classifier: Programming Language :: Python :: 3.10
Classifier: Topic :: Scientific/Engineering :: Artificial Intelligence
Classifier: Topic :: Scientific/Engineering
Classifier: Intended Audience :: Education
Classifier: Intended Audience :: Developers
Requires-Python: >=3.7
License-File: LICENSE.md
